{
  "Type": "Variant",
  "Reference": "Template_Pkmn_Predator",
  "Modify": {
    "Appearance": "Pkmn_Ekans",
    "AttitudeGroup": "Pkmn_Predators",
    "DropList": "Drop_Pkmn_T0_Hide",
    "Type1": "PoisonType",
    "WildLevelMin": 5,
    "WildLevelMax": 22,
    "MaxSpeed": 5.5,
    "CaptureDifficulty": 1.0,
    "TameRoleChange": "Pkmn_Ekans_Tamed",
    "FlockArray": [
      "Pkmn_Ekans",
      "Pkmn_Arbok"
    ],
    "IsMemory": true,
    "MemoriesCategory": "Reptile",
    "MemoriesNameOverride": "Ekans",
    "Attack": "Root_Pkmn_Attack_Melee",
    "_InteractionVars": {
    },
    "NameTranslationKey": {
      "Compute": "NameTranslationKey"
    }
  },
  "Parameters": {
    "NameTranslationKey": {
      "Value": "server.npcRoles.Pkmn_Ekans.name",
      "Description": "Translation key for NPC name display"
    }
  }
}
