{
  "Type": "Variant",
  "Reference": "Template_Pkmn_Tamed",
  "Modify": {
    "Appearance": "Pkmn_Vulpix",
    "DropList": "Drop_Pkmn_T0_Hide",
    "AttractiveItemSet": [
      "Food_Kebab_Fruit"
    ],
    "Type1": "FireType",
    "IsMountable": false,
    "MountAnchorX":0,
    "MountAnchorY":1,
    "MountAnchorZ":0,
    "AttractiveItemSetParticles": "Want_Food_Corn",
    "MaxHealth": 38,
    "MaxSpeed": 8,
    "WanderRadius": 10,
    "ViewRange": 12,
    "HearingRange": 8,
    "AbsoluteDetectionRange": 2,
    "AlertedRange": 18,
    "Attack": "Root_Pkmn_Attack_Melee",
    "AttackDistance": 2.5,
    "CombatBehaviorDistance": 6,
    "IsMemory": true,
    "MemoriesCategory": "Predator",
    "MemoriesNameOverride": "Vulpix",
    "NameTranslationKey": {
      "Compute": "NameTranslationKey"
    }
  },
  "Parameters": {
    "NameTranslationKey": {
      "Value": "server.npcRoles.Pkmn_Vulpix.name",
      "Description": "Translation key for NPC name display"
    }
  }
}
