{
  "Parent": "Template_Pkmn_Bi",
  "Model": "NPC/Pkmn/Machamp/Models/Model.blockymodel",
  "Texture": "NPC/Pkmn/Machamp/Models/Texture.png",
  "Icon": "Icons/ModelsGenerated/Pkmn_Machamp.png",
  "AnimationSets": {
    "Alerted": {
      "Animations": [
        {
          "Animation": "NPC/Pkmn/Machamp/Animations/Default/Alerted.blockyanim",
          "Looping": false,
          "SoundEventId": "SFX_Pkmn_Machamp_Cry"
        }
      ]
    },
    "Spawn": {
      "Animations": [
        {
          "Animation": "NPC/Pkmn/Machamp/Animations/Default/Spawn.blockyanim",
          "BlendingDuration": 0,
          "Looping": false,
          "SoundEventId": "SFX_Pkmn_Machamp_Cry"
        }
      ]
    }
  }
}