{
    "Parent": "Template_Pkmn_Bi",
    "Model": "NPC/Pkmn/Marowak/Models/Model.blockymodel",
    "Texture": "NPC/Pkmn/Marowak/Models/Texture.png",
    "Icon": "Icons/ModelsGenerated/Pkmn_Marowak.png",
    "AnimationSets": {
        "Alerted": {
            "Animations": [
                {
                    "Animation": "NPC/Pkmn/Marowak/Animations/Default/Alerted.blockyanim",
                    "Looping": false,
                    "SoundEventId": "SFX_Pkmn_Marowak_Cry"
                }
            ]
        },
        "Spawn": {
            "Animations": [
                {
                    "Animation": "NPC/Pkmn/Marowak/Animations/Default/Spawn.blockyanim",
                    "BlendingDuration": 0,
                    "Looping": false,
                    "SoundEventId": "SFX_Pkmn_Marowak_Cry"
                }
            ]
        },
        "Bite": {
            "Animations": [
                {
                    "Animation": "NPC/Pkmn/Marowak/Animations/Attacks/Bite.blockyanim"
                }
            ]
        },
        "BiteMoving": {
            "Animations": [
                {
                    "Animation": "NPC/Pkmn/Marowak/Animations/Attacks/Bite_Moving.blockyanim"
                }
            ]
        },
        "Death": {
            "Animations": [
                {
                    "Animation": "NPC/Pkmn/Marowak/Animations/Damage/Death.blockyanim",
                    "Looping": false
                }
            ]
        },
        "Hurt": {
            "Animations": [
                {
                    "Animation": "NPC/Pkmn/Marowak/Animations/Damage/Hurt.blockyanim",
                    "Looping": false
                }
            ]
        },
        "Hurt2": {
            "Animations": [
                {
                    "Animation": "NPC/Pkmn/Marowak/Animations/Damage/Hurt2.blockyanim"
                }
            ]
        },
        "Crouch": {
            "Animations": [
                {
                    "Animation": "NPC/Pkmn/Marowak/Animations/Default/Crouch.blockyanim"
                }
            ]
        },
        "CrouchWalk": {
            "Animations": [
                {
                    "Animation": "NPC/Pkmn/Marowak/Animations/Default/Crouch_Walk.blockyanim"
                }
            ]
        },
        "CrouchWalkBackward": {
            "Animations": [
                {
                    "Animation": "NPC/Pkmn/Marowak/Animations/Default/Crouch_Walk_Backward.blockyanim"
                }
            ]
        },
        "Fall": {
            "Animations": [
                {
                    "Animation": "NPC/Pkmn/Marowak/Animations/Default/Fall.blockyanim"
                }
            ]
        },
        "FallFar": {
            "Animations": [
                {
                    "Animation": "NPC/Pkmn/Marowak/Animations/Default/Fall_Far.blockyanim"
                }
            ]
        },
        "Idle": {
            "Animations": [
                {
                    "Animation": "NPC/Pkmn/Marowak/Animations/Default/Idle.blockyanim"
                }
            ]
        },
        "Jump": {
            "Animations": [
                {
                    "Animation": "NPC/Pkmn/Marowak/Animations/Default/Jump.blockyanim",
                    "Looping": false
                }
            ]
        },
        "JumpFar": {
            "Animations": [
                {
                    "Animation": "NPC/Pkmn/Marowak/Animations/Default/Jump_Far.blockyanim",
                    "Looping": false
                }
            ]
        },
        "JumpFar2": {
            "Animations": [
                {
                    "Animation": "NPC/Pkmn/Marowak/Animations/Default/Jump_Far2.blockyanim"
                }
            ]
        },
        "Laydown": {
            "Animations": [
                {
                    "Animation": "NPC/Pkmn/Marowak/Animations/Default/Laydown.blockyanim",
                    "Looping": false
                }
            ]
        },
        "Run": {
            "Animations": [
                {
                    "Animation": "NPC/Pkmn/Marowak/Animations/Default/Run.blockyanim"
                }
            ]
        },
        "Sleep": {
            "Animations": [
                {
                    "Animation": "NPC/Pkmn/Marowak/Animations/Default/Sleep.blockyanim"
                }
            ]
        },
        "Wake": {
            "Animations": [
                {
                    "Animation": "NPC/Pkmn/Marowak/Animations/Default/Wake.blockyanim",
                    "Looping": false
                }
            ]
        },
        "Walk": {
            "Animations": [
                {
                    "Animation": "NPC/Pkmn/Marowak/Animations/Default/Walk.blockyanim"
                }
            ]
        },
        "WalkBackward": {
            "Animations": [
                {
                    "Animation": "NPC/Pkmn/Marowak/Animations/Default/Walk_Backward.blockyanim"
                }
            ]
        },
        "LookAround": {
            "Animations": [
                {
                    "Animation": "NPC/Pkmn/Marowak/Animations/Flavor/Look_Around.blockyanim"
                }
            ]
        },
        "LookLeft": {
            "Animations": [
                {
                    "Animation": "NPC/Pkmn/Marowak/Animations/Flavor/Look_Left.blockyanim"
                }
            ]
        },
        "LookRight": {
            "Animations": [
                {
                    "Animation": "NPC/Pkmn/Marowak/Animations/Flavor/Look_Right.blockyanim"
                }
            ]
        },
        "Roar": {
            "Animations": [
                {
                    "Animation": "NPC/Pkmn/Marowak/Animations/Flavor/Roar.blockyanim"
                }
            ]
        },
        "SniffLeft": {
            "Animations": [
                {
                    "Animation": "NPC/Pkmn/Marowak/Animations/Flavor/Sniff_Left.blockyanim"
                }
            ]
        },
        "SniffRight": {
            "Animations": [
                {
                    "Animation": "NPC/Pkmn/Marowak/Animations/Flavor/Sniff_Right.blockyanim"
                }
            ]
        },
        "Fly": {
            "Animations": [
                {
                    "Animation": "NPC/Pkmn/Marowak/Animations/Fly/Fly.blockyanim"
                }
            ]
        },
        "FlyBackward": {
            "Animations": [
                {
                    "Animation": "NPC/Pkmn/Marowak/Animations/Fly/Fly_Backward.blockyanim"
                }
            ]
        },
        "FlyFast": {
            "Animations": [
                {
                    "Animation": "NPC/Pkmn/Marowak/Animations/Fly/Fly_Fast.blockyanim"
                }
            ]
        },
        "FlyIdle": {
            "Animations": [
                {
                    "Animation": "NPC/Pkmn/Marowak/Animations/Fly/Fly_Idle.blockyanim"
                }
            ]
        },
        "Swim": {
            "Animations": [
                {
                    "Animation": "NPC/Pkmn/Marowak/Animations/Swim/Swim.blockyanim"
                }
            ]
        },
        "SwimBackward": {
            "Animations": [
                {
                    "Animation": "NPC/Pkmn/Marowak/Animations/Swim/Swim_Backward.blockyanim"
                }
            ]
        },
        "SwimFast": {
            "Animations": [
                {
                    "Animation": "NPC/Pkmn/Marowak/Animations/Swim/Swim_Fast.blockyanim"
                }
            ]
        },
        "SwimIdle": {
            "Animations": [
                {
                    "Animation": "NPC/Pkmn/Marowak/Animations/Swim/Swim_Idle.blockyanim"
                }
            ]
        },
        "SwimJump": {
            "Animations": [
                {
                    "Animation": "NPC/Pkmn/Marowak/Animations/Swim/Swim_Jump.blockyanim",
                    "Looping": false
                }
            ]
        }
    }
}